{"authorDailyContributionsMap":{"whatthelump":[{"date":"2021-02-21","commitResults":[{"hash":"a0cbe0a10b3ca196e18def667413c9796c7282a9","messageTitle":"Update UG - Delete command","messageBody":"Fixes #14","fileTypesAndContributionMap":{"docs":{"insertions":6,"deletions":7}}}]},{"date":"2021-02-22","commitResults":[{"hash":"0d80806221a41203ec5bb86d2ef115d0cef8e6a2","messageTitle":"Fixes #9","messageBody":"","fileTypesAndContributionMap":{"docs":{"insertions":5,"deletions":6}}}]},{"date":"2021-02-25","commitResults":[{"hash":"30e0586d30c9af7134604b15f7452696a0c6b1e4","messageTitle":"Update DeveloperGuide.md","messageBody":"Update product scope","fileTypesAndContributionMap":{"docs":{"insertions":9,"deletions":7}}}]},{"date":"2021-02-28","commitResults":[{"hash":"534fba2f3a06c5785b6ce9681fedf7277a23c15c","messageTitle":"Update DeveloperGuide.md","messageBody":"Removed the point about updating cleaning agency under Product Scope","fileTypesAndContributionMap":{"docs":{"insertions":0,"deletions":1}}},{"hash":"87e165eb56d2bd87e3540e8d711c194a176d9560","messageTitle":"Add remark command","messageBody":"","fileTypesAndContributionMap":{"functional-code":{"insertions":527,"deletions":0}}},{"hash":"1fa3dc912538ac75da3d016312c9cbd6a16ecdbc","messageTitle":"Update NameContainsKeywordsPredicate.java","messageBody":"Fixed the ordering of import statements","fileTypesAndContributionMap":{"functional-code":{"insertions":2,"deletions":2}}},{"hash":"65a9769c3ea6a74b42b0b71a56b23b659d5fb035","messageTitle":"Update Person.java","messageBody":"Fixed the ordering of import statements","fileTypesAndContributionMap":{"functional-code":{"insertions":2,"deletions":2}}},{"hash":"13301cce49a98f777734e7bf5b96cfcc77f07f9d","messageTitle":"Update UniquePersonList.java","messageBody":"Fixed the ordering of import statements","fileTypesAndContributionMap":{"functional-code":{"insertions":6,"deletions":6}}}]},{"date":"2021-03-05","commitResults":[{"hash":"715a460ef7ba42817ffba292645692fbfb835ef9","messageTitle":"Update UserGuide.md - Removed traces of AB3","messageBody":"Also changed any mention of \u0027apartment\u0027 to \u0027residence\u0027 to standardize naming convention","fileTypesAndContributionMap":{"docs":{"insertions":28,"deletions":28}}}]},{"date":"2021-03-11","commitResults":[{"hash":"98d6b66250a2a2ff5286514bfa9628887d0d6d92","messageTitle":"Morph Logic and Storage, replace AddressBook with ResidenceTracker","messageBody":"","fileTypesAndContributionMap":{"functional-code":{"insertions":148,"deletions":146},"other":{"insertions":87,"deletions":86},"test-code":{"insertions":63,"deletions":63}}}]},{"date":"2021-03-12","commitResults":[{"hash":"bda26aadc6b45bd5524990097dfaaa1d445e82a4","messageTitle":"Update MainApp.java","messageBody":"Changed ordering of import statements to match lexicographical order","fileTypesAndContributionMap":{"functional-code":{"insertions":2,"deletions":2}}},{"hash":"c708f2578e9a007bd8b6113909099a8c51ebc3ea","messageTitle":"Update MainApp.java","messageBody":"Split line 59 into two lines to avoid exceeding 120 characters.","fileTypesAndContributionMap":{"functional-code":{"insertions":2,"deletions":1}}},{"hash":"a5c2744873dfe76570f74cf24e525b388ae49d3b","messageTitle":"Update ClearCommand.java","messageBody":"Changed ordering of import statements to match lexicographical order.","fileTypesAndContributionMap":{"functional-code":{"insertions":1,"deletions":1}}},{"hash":"ba4aa65ee80600ccaf3af01b4e9f4af55c07bf68","messageTitle":"Update SampleDataUtil.java","messageBody":"Changed the ordering of import statements to match lexicographical order.","fileTypesAndContributionMap":{"functional-code":{"insertions":1,"deletions":1}}},{"hash":"4f6f3cc5bd8713bd44e570f0b08c6fc7a2e8d669","messageTitle":"Update JsonSerializableResidenceTracker.java","messageBody":"Changed the ordering of import statements to match lexicographical order.","fileTypesAndContributionMap":{"functional-code":{"insertions":1,"deletions":1}}},{"hash":"fa5b25dc2a0459bcfef6dd1647dcd433045bae5c","messageTitle":"Update StorageManager.java","messageBody":"Split line 63 to avoid exceeding 120 characters.","fileTypesAndContributionMap":{"functional-code":{"insertions":2,"deletions":1}}},{"hash":"9abb1b3046bbc072b89fe61d805303b9da9b9916","messageTitle":"Update MainApp.java","messageBody":"Remove trailing whitespace.","fileTypesAndContributionMap":{"functional-code":{"insertions":1,"deletions":1}}},{"hash":"dd7b96b19c753be0348acd76a0425db52b8d517b","messageTitle":"Update StorageManager.java","messageBody":"Remove trailing whitespace.","fileTypesAndContributionMap":{"functional-code":{"insertions":1,"deletions":1}}},{"hash":"0a6ef54961b4314f2b5a9112a2ed4064f7bed712","messageTitle":"Update AddCommandTest.java","messageBody":"Changed the ordering of imports to match lexicographical order.","fileTypesAndContributionMap":{"test-code":{"insertions":1,"deletions":1}}},{"hash":"affe019e00dd468385f6151209fb4c7d3a3800ae","messageTitle":"Update ClearCommandTest.java","messageBody":"Changed the ordering of imports to match lexicographical order.","fileTypesAndContributionMap":{"test-code":{"insertions":1,"deletions":1}}},{"hash":"655e21d4fdf512a6b4d9e560d17f4327c7684183","messageTitle":"Update CommandTestUtil.java","messageBody":"Changed the ordering of imports to match lexicographical order.","fileTypesAndContributionMap":{"test-code":{"insertions":1,"deletions":1}}},{"hash":"431a480fbcbdb28d3bbc23adb0f4947365a377af","messageTitle":"Update EditCommandTest.java","messageBody":"Changed the ordering of imports to match lexicographical order.","fileTypesAndContributionMap":{"test-code":{"insertions":1,"deletions":1}}},{"hash":"7d8ec30c455c7bc655de1a6e9b85f75564052810","messageTitle":"Update JsonResidenceTrackerStorageTest.java","messageBody":"Changed ordering of import statements to match lexicographical order and split line 34 to avoid exceeding 120 characters.","fileTypesAndContributionMap":{"test-code":{"insertions":3,"deletions":2}}},{"hash":"25c13a08b5eb0e0f9e3c1e49184106504ab6e07f","messageTitle":"Update StorageManagerTest.java","messageBody":"Changed the ordering of import statements to match lexicographical order.","fileTypesAndContributionMap":{"test-code":{"insertions":1,"deletions":1}}}]},{"date":"2021-03-15","commitResults":[{"hash":"ab7c0e15cb6249d68a5f9ba7dfa5a0492ea8f393","messageTitle":"Replace occurrences of AddressBook with ResidenceTracker","messageBody":"","fileTypesAndContributionMap":{"functional-code":{"insertions":20,"deletions":20},"test-code":{"insertions":5,"deletions":5}}}]},{"date":"2021-03-16","commitResults":[{"hash":"53de7b60dff09e8318a156552ab89416bb7d655b","messageTitle":"Update AddCommandParserTest.java to use Residences instead of Persons. Also made appropriate changes to CommandTestUtil.java.","messageBody":"","fileTypesAndContributionMap":{"functional-code":{"insertions":19,"deletions":19},"test-code":{"insertions":95,"deletions":78}}},{"hash":"b94b64050018b58fab2e0f191d90075c56625254","messageTitle":"Update AddCommand.java","messageBody":"Changed import from wildcard to specific classes imported","fileTypesAndContributionMap":{"functional-code":{"insertions":5,"deletions":1}}},{"hash":"a3aca2a7ea89de35645b9d40a32199ad3e0743d8","messageTitle":"Update CommandTestUtil.java","messageBody":"Fixed accidental refactoring of EMAIL_DESC_BOB to VOID (should be removed later)","fileTypesAndContributionMap":{"test-code":{"insertions":1,"deletions":1}}},{"hash":"da70329d67b29114bcd19c553375595cdbaa314c","messageTitle":"Update AddCommandParserTest.java","messageBody":"Removed tests under parse_compulsoryFieldMissing_failure() method to reflect that Booking and CleanStatusTag are optional","fileTypesAndContributionMap":{"test-code":{"insertions":2,"deletions":12}}},{"hash":"5d1f51bcb3257f4fd24385f7b1d338b0b8932714","messageTitle":"Update AddCommandParserTest.java","messageBody":"Updated parse_optionalFieldsMissing_success() method to reflect that Booking and CleanStatusTag are optional","fileTypesAndContributionMap":{"test-code":{"insertions":10,"deletions":1}}}]},{"date":"2021-03-17","commitResults":[{"hash":"0a7c91d347df163ae6d081efa8277bc8077ae2b0","messageTitle":"Update AddCommandParserTest.java","messageBody":"Remove trailing whitespace","fileTypesAndContributionMap":{"test-code":{"insertions":3,"deletions":3}}},{"hash":"c999a01ecde483bdefd4480185018e7fe6d55887","messageTitle":"Fix checkstyle, mainly import statements and exceeding 120 character limit for single lines.","messageBody":"","fileTypesAndContributionMap":{"test-code":{"insertions":102,"deletions":66}}},{"hash":"09676f2f2bdaf5f51d4738e2ac45551a2d6a3e84","messageTitle":"Update DeleteCommand.java, replaced occurrences of Person with Residence.","messageBody":"","fileTypesAndContributionMap":{"functional-code":{"insertions":7,"deletions":7}}}]},{"date":"2021-03-18","commitResults":[{"hash":"e5ccade2daf410a2fe46855089a94f7b7288bc17","messageTitle":"Update examples for add and edit commands in HelpWindow.java","messageBody":"","fileTypesAndContributionMap":{"functional-code":{"insertions":4,"deletions":4},"test-code":{"insertions":0,"deletions":1}}}]},{"date":"2021-03-19","commitResults":[{"hash":"fc97de1b7e4824f76b21ac3ad6f71cb19d658a88","messageTitle":"Fix checkstyle: ordering of imports and not exceeding 120 characters for single line.","messageBody":"","fileTypesAndContributionMap":{"test-code":{"insertions":4,"deletions":4}}},{"hash":"2dcdbce5a27ae3b6be944cbb86bdd645f345395d","messageTitle":"Fixed some tests.","messageBody":"","fileTypesAndContributionMap":{"test-code":{"insertions":14,"deletions":12}}}]},{"date":"2021-03-21","commitResults":[{"hash":"5f68a08a51784d3969d89362678d159c8dd3fbd6","messageTitle":"Update UserGuide.md","messageBody":"Fixes #77","fileTypesAndContributionMap":{"docs":{"insertions":7,"deletions":7}}},{"hash":"d6769d450a03d6bf95d822ad4be4d4c7c05afe78","messageTitle":"Enable assertions when executing java code","messageBody":"","fileTypesAndContributionMap":{"other":{"insertions":4,"deletions":0}}}]},{"date":"2021-03-22","commitResults":[{"hash":"81bfd583f2752f74418e3baff61bbaeb213521ff","messageTitle":"Morph Person class to Booking class, created BookingTest.java.","messageBody":"","fileTypesAndContributionMap":{"functional-code":{"insertions":257,"deletions":299},"other":{"insertions":5,"deletions":1},"docs":{"insertions":3,"deletions":3},"test-code":{"insertions":191,"deletions":140}}}]},{"date":"2021-03-23","commitResults":[{"hash":"cef3e18e184f6486c427b10faa7c4e65040aa88e","messageTitle":"Morph Person class to Booking class, created BookingTest.java.","messageBody":"","fileTypesAndContributionMap":{"functional-code":{"insertions":158,"deletions":161},"other":{"insertions":2,"deletions":2},"test-code":{"insertions":15,"deletions":15}}},{"hash":"9d593419b5f61830d7757f54ab067eddb0c24615","messageTitle":"Morph Person class to Booking class, created BookingTest.java.","messageBody":"","fileTypesAndContributionMap":{"functional-code":{"insertions":9,"deletions":9},"other":{"insertions":9,"deletions":13},"test-code":{"insertions":30,"deletions":26}}},{"hash":"53ed30defa72c834927e8cfc39361dd5082f8614","messageTitle":"Morph Person class to Booking class, created BookingTest.java.","messageBody":"","fileTypesAndContributionMap":{"functional-code":{"insertions":3,"deletions":3}}},{"hash":"8603e3f8f96aa3f950231a6991211af41719f8a3","messageTitle":"Changed ordering of import statements to match lexicographical order.","messageBody":"","fileTypesAndContributionMap":{"functional-code":{"insertions":1,"deletions":1}}},{"hash":"4088a5ea35828b3b82fb919557b4767b35613da5","messageTitle":"Changed ordering of import statements to match lexicographical order.","messageBody":"","fileTypesAndContributionMap":{"other":{"insertions":12,"deletions":22},"test-code":{"insertions":1,"deletions":1}}},{"hash":"8129a454d4280ca8310063c3e40bca72143a4a8d","messageTitle":"Removed redundant imports.","messageBody":"","fileTypesAndContributionMap":{"test-code":{"insertions":0,"deletions":5}}}]},{"date":"2021-03-24","commitResults":[{"hash":"5591e299f198df4cee46b08ee83a0e8303901696","messageTitle":"Update TypicalIndexes.java","messageBody":"Fixed minor typo.","fileTypesAndContributionMap":{"test-code":{"insertions":1,"deletions":1}}},{"hash":"a4c424b5ca8e34c81b760ef071289f7af8fb9068","messageTitle":"Update StatusCommandParser.java","messageBody":"Replaced reference to EditCommand with StatusCommand.","fileTypesAndContributionMap":{"functional-code":{"insertions":1,"deletions":1}}},{"hash":"5d5146d0ad650e331a3a737c6baf74311a562556","messageTitle":"Added doesOverlap method under Booking class.","messageBody":"","fileTypesAndContributionMap":{"functional-code":{"insertions":25,"deletions":15}}}]},{"date":"2021-03-25","commitResults":[{"hash":"8bbea7e4fb9dfe70eeb2524596467399a8a0d369","messageTitle":"Updated documentation in UniqueBookingList.java","messageBody":"","fileTypesAndContributionMap":{"functional-code":{"insertions":23,"deletions":10}}},{"hash":"a35b37b7e637f3a8d0863a2fa64420daf44e4bfd","messageTitle":"Update Booking.java","messageBody":"Added whitespace before and after \u0027||\u0027 operator","fileTypesAndContributionMap":{"functional-code":{"insertions":1,"deletions":1}}}]},{"date":"2021-03-28","commitResults":[{"hash":"648fa586b8db284fc694d695f829ade6687f1fce","messageTitle":"Updated documentation related to Booking class.","messageBody":"","fileTypesAndContributionMap":{"functional-code":{"insertions":6,"deletions":7},"docs":{"insertions":24,"deletions":12},"test-code":{"insertions":0,"deletions":10}}},{"hash":"726c3d0ddc390fefbdd20aa08f207568baaf73ec","messageTitle":"Updated HelpWindow.java with Add Booking and Delete Booking commands.","messageBody":"","fileTypesAndContributionMap":{"functional-code":{"insertions":15,"deletions":2}}},{"hash":"86590ce595f91ed4c626501989be984931e212f8","messageTitle":"Update UserGuide.md with AddBooking Command.","messageBody":"","fileTypesAndContributionMap":{"functional-code":{"insertions":5,"deletions":5},"docs":{"insertions":21,"deletions":10}}},{"hash":"4d490c09f28d7d1b81420e28c5ba41aed20d29f1","messageTitle":"Removed references to booking details.","messageBody":"","fileTypesAndContributionMap":{"docs":{"insertions":3,"deletions":3}}},{"hash":"56d5e2c6cb95b2ac92f7767dcbb1f647b016b93f","messageTitle":"Removed references to booking details.","messageBody":"","fileTypesAndContributionMap":{"docs":{"insertions":2,"deletions":2}}}]},{"date":"2021-03-30","commitResults":[{"hash":"a824fbd19342d2006616185c7edfbbbac06b0d9e","messageTitle":"Updated documentation for Command files.","messageBody":"","fileTypesAndContributionMap":{"functional-code":{"insertions":23,"deletions":19},"test-code":{"insertions":15,"deletions":89}}},{"hash":"6a2b9c0fa643ff37248b39a8d2869160dc5dd57d","messageTitle":"Update CommandTestUtil.java","messageBody":"Remove unused imports","fileTypesAndContributionMap":{"test-code":{"insertions":0,"deletions":2}}},{"hash":"4b06342e605a4c4aa90cc410f9a41c7398841aea","messageTitle":"Update CommandTestUtil.java","messageBody":"Replaced references to Person (e.g. \"Amy\", \"Bob) with Booking.","fileTypesAndContributionMap":{"test-code":{"insertions":9,"deletions":2}}}]},{"date":"2021-04-01","commitResults":[{"hash":"f0ba6f95ee129de12d0545f87edf6100c8e61296","messageTitle":"Update Residence.java","messageBody":"Changed the range of booking dates showing as upcoming bookings from 6 days (from the current date) to 7 days (from the current date).","fileTypesAndContributionMap":{"functional-code":{"insertions":1,"deletions":1}}}]},{"date":"2021-04-07","commitResults":[{"hash":"48bb1a02ca30e3a2dd98bb10217c4ab5368449e5","messageTitle":"Update UserGuide.md","messageBody":"Minor grammatical issues","fileTypesAndContributionMap":{"docs":{"insertions":5,"deletions":5}}},{"hash":"832c8bd60d2f79c7086ed500b77d84f950a6397e","messageTitle":"Updated UG and help window based on PE dry run feedback","messageBody":"","fileTypesAndContributionMap":{"functional-code":{"insertions":14,"deletions":12},"docs":{"insertions":1,"deletions":0}}},{"hash":"8f76a401e3d5a6abb08e242ad575ce88cade3661","messageTitle":"Update ResidenceName.java","messageBody":"Fix checkstyle issue","fileTypesAndContributionMap":{"functional-code":{"insertions":2,"deletions":2}}}]}],"awzhenyi":[{"date":"2021-02-24","commitResults":[{"hash":"7da8f7e91ccd89ad52cd96350d9bfbd6249ff93b","messageTitle":"Update AboutUs","messageBody":"","fileTypesAndContributionMap":{"docs":{"insertions":5,"deletions":6}}},{"hash":"3e11f460db98300e4a81aba92db7ef3a81a6d1e9","messageTitle":"Update README.md","messageBody":"","fileTypesAndContributionMap":{"docs":{"insertions":7,"deletions":2}}},{"hash":"c3eff6f68c29f99dcbfd28fcda8f8e7147e057ee","messageTitle":"Update UserGuide.md","messageBody":"","fileTypesAndContributionMap":{"docs":{"insertions":9,"deletions":12}}},{"hash":"f1b18c41b1dc495d799f7006e873ecaecc8ca63b","messageTitle":"Update README.md","messageBody":"Edit typo","fileTypesAndContributionMap":{"docs":{"insertions":1,"deletions":1}}},{"hash":"76bd0da04d19aec8a166162128d176e58eba7c53","messageTitle":"Update UserGuide.md","messageBody":"","fileTypesAndContributionMap":{"docs":{"insertions":1,"deletions":1}}},{"hash":"2de7b62b722a942ccfc3a58ec7fd4d1f645f120b","messageTitle":"Update UserGuide.md","messageBody":"","fileTypesAndContributionMap":{"docs":{"insertions":3,"deletions":3}}}]},{"date":"2021-03-02","commitResults":[{"hash":"a1d6a7163fde949eaa409c54b73a109c8324af79","messageTitle":"Rename residence package","messageBody":"","fileTypesAndContributionMap":{"functional-code":{"insertions":194,"deletions":284},"other":{"insertions":24,"deletions":33},"test-code":{"insertions":11,"deletions":11}}},{"hash":"050bd99549e8a0bec2e18102f2032cc14abc6eda","messageTitle":"Update Developer Guide","messageBody":"","fileTypesAndContributionMap":{"docs":{"insertions":6,"deletions":2}}},{"hash":"3abec01236000ba8d39f826294bfcb8583fabae7","messageTitle":"Fix Formatting","messageBody":"","fileTypesAndContributionMap":{"functional-code":{"insertions":17,"deletions":15}}},{"hash":"fec6a1aff21eb0a651cee28a3a721980b70bfdfa","messageTitle":"Fix Formatting","messageBody":"","fileTypesAndContributionMap":{"functional-code":{"insertions":6,"deletions":6}}},{"hash":"9443ea5d7c1e50585fad37d533abf89331ca545b","messageTitle":"Fix Formatting","messageBody":"","fileTypesAndContributionMap":{"functional-code":{"insertions":18,"deletions":18}}},{"hash":"588c1bab3d9ff424d92a35181c2fc66c0f82972e","messageTitle":"Fix Formatting","messageBody":"","fileTypesAndContributionMap":{"functional-code":{"insertions":6,"deletions":6},"test-code":{"insertions":11,"deletions":11}}},{"hash":"148632f271f7432e58120c7d28e1f04d52780253","messageTitle":"Fix Formatting","messageBody":"","fileTypesAndContributionMap":{"functional-code":{"insertions":1,"deletions":1}}},{"hash":"7184ff0b390c73593330221f2637ac10ee15f6ef","messageTitle":"Update DuplicateResidenceException.java","messageBody":"","fileTypesAndContributionMap":{"functional-code":{"insertions":1,"deletions":1}}},{"hash":"7265722dba01419aa2ec7996831faf9a5f044f5a","messageTitle":"Update DuplicateResidenceException.java","messageBody":"","fileTypesAndContributionMap":{"functional-code":{"insertions":1,"deletions":1}}}]},{"date":"2021-03-14","commitResults":[{"hash":"70b5d8921468a624354abcca2d188f3ea1f00fe3","messageTitle":"Changed EditCommand","messageBody":"","fileTypesAndContributionMap":{"functional-code":{"insertions":182,"deletions":196}}},{"hash":"ab04c6ad6e9c74ecc2ad83619d251c0f76e0d0b9","messageTitle":"Morph Person to Residence","messageBody":"","fileTypesAndContributionMap":{"functional-code":{"insertions":294,"deletions":75}}},{"hash":"3cc31ff220db1d853b164845ecadb9df0ccc2edd","messageTitle":"Update ResidenceCard.java","messageBody":"","fileTypesAndContributionMap":{"functional-code":{"insertions":1,"deletions":1}}},{"hash":"1c0496b606b11d75738e62b9f15c42d256662c6e","messageTitle":"Morph Person into Residences","messageBody":"","fileTypesAndContributionMap":{"functional-code":{"insertions":44,"deletions":0}}},{"hash":"987d71e013a5acf15d661093dde1e53b02e7239e","messageTitle":"Fix Checkstyle","messageBody":"","fileTypesAndContributionMap":{"functional-code":{"insertions":0,"deletions":1}}}]},{"date":"2021-03-15","commitResults":[{"hash":"b9cb037220c14254d435ebbf56ba39513a7d6b2e","messageTitle":"Update EditCommand Tests","messageBody":"","fileTypesAndContributionMap":{"functional-code":{"insertions":8,"deletions":8},"test-code":{"insertions":271,"deletions":57}}},{"hash":"c76d629bdb53c9b9c23edfcc630764019f83ec35","messageTitle":"Change some tests from Person to Residence","messageBody":"","fileTypesAndContributionMap":{"functional-code":{"insertions":3,"deletions":1},"test-code":{"insertions":85,"deletions":112}}},{"hash":"4a9541c11080dc9b7a124e4f77258e0ed0c7f8c2","messageTitle":"Update Tests","messageBody":"","fileTypesAndContributionMap":{"test-code":{"insertions":31,"deletions":30}}},{"hash":"b5d36e5a4e3d0d81d3bde66c8ee000f18f0dcc53","messageTitle":"Update AddCommandParserTest.java","messageBody":"","fileTypesAndContributionMap":{"test-code":{"insertions":3,"deletions":2}}}]},{"date":"2021-03-17","commitResults":[{"hash":"a7439f9ae1eb2f75b593b2ae575f560118384aab","messageTitle":"Fix Checkstyle","messageBody":"","fileTypesAndContributionMap":{"test-code":{"insertions":15,"deletions":13}}},{"hash":"2dca8bdffbd218ac7965231acb0b54fd7b1d8838","messageTitle":"Fix Tests","messageBody":"","fileTypesAndContributionMap":{"test-code":{"insertions":4,"deletions":4}}}]},{"date":"2021-03-18","commitResults":[{"hash":"666534097abe9a1ca70eddef400efc4c3194aa85","messageTitle":"Fix Tests","messageBody":"","fileTypesAndContributionMap":{"functional-code":{"insertions":1,"deletions":0},"test-code":{"insertions":40,"deletions":35}}}]},{"date":"2021-03-26","commitResults":[{"hash":"edf2c9bed1b0c40ef02b20ea2ac76e8d03c84565","messageTitle":"Add Sort and DeleteBooking command","messageBody":"","fileTypesAndContributionMap":{"functional-code":{"insertions":109,"deletions":6},"test-code":{"insertions":1,"deletions":1}}}]},{"date":"2021-03-27","commitResults":[{"hash":"476f81254bcef5a309e47a4f1bfc7e02631e7336","messageTitle":"Add DeleteBookingCommandParser","messageBody":"","fileTypesAndContributionMap":{"functional-code":{"insertions":73,"deletions":9}}},{"hash":"aa94d07149391d1de237899bbb71a08dc6101c19","messageTitle":"Update DeleteBookingCommand on User Guide","messageBody":"","fileTypesAndContributionMap":{"docs":{"insertions":12,"deletions":0}}},{"hash":"db923f0280e705fa9d576384ca45e733c163cde6","messageTitle":"Add Skeleton Code for DeleteBookingCommandTest","messageBody":"","fileTypesAndContributionMap":{"functional-code":{"insertions":27,"deletions":18},"test-code":{"insertions":24,"deletions":1}}},{"hash":"f32f668dc2c09ee53d5f7d7db46e3558ba1572cd","messageTitle":"Fix Custom Comparator","messageBody":"","fileTypesAndContributionMap":{"functional-code":{"insertions":1,"deletions":10},"test-code":{"insertions":0,"deletions":24}}},{"hash":"94fde9836da7de10b629d9d81afedaa23ee21612","messageTitle":"Fix Checkstyle","messageBody":"","fileTypesAndContributionMap":{"functional-code":{"insertions":0,"deletions":1}}},{"hash":"367025c0bc451a8f67f727834350b8c5ecb02ed8","messageTitle":"Fix errors","messageBody":"","fileTypesAndContributionMap":{"functional-code":{"insertions":4,"deletions":3}}}]},{"date":"2021-03-28","commitResults":[{"hash":"eab1a0a6242c08197748b48bf6dc15400509993b","messageTitle":"Refactor bookingDetails to booking","messageBody":"","fileTypesAndContributionMap":{"functional-code":{"insertions":9,"deletions":9},"test-code":{"insertions":6,"deletions":6}}},{"hash":"46ff7a6240b569628601f8236af1ec30ac2b0e73","messageTitle":"Change DeleteBookingCommand to take in prefixes","messageBody":"","fileTypesAndContributionMap":{"functional-code":{"insertions":33,"deletions":29}}},{"hash":"98a457cdc92fa42e0cf9a07ef1116cf961ea8904","messageTitle":"Update User Guide","messageBody":"","fileTypesAndContributionMap":{"docs":{"insertions":2,"deletions":2}}},{"hash":"4adba1704a95bb29da6fe7f00b7fa08d0c676c7f","messageTitle":"Create EditBookingCommand","messageBody":"","fileTypesAndContributionMap":{"functional-code":{"insertions":192,"deletions":0}}},{"hash":"00bc92f7fed794fbcc74a738c1adee50e5eb47c6","messageTitle":"Fix EditBookingCommand bugs","messageBody":"","fileTypesAndContributionMap":{"functional-code":{"insertions":131,"deletions":26}}},{"hash":"3f01a562d5543c829b9ca1417389f85e4600145b","messageTitle":"Add javadocs and fix some documentation","messageBody":"","fileTypesAndContributionMap":{"functional-code":{"insertions":35,"deletions":21}}},{"hash":"fcf109abd129553ddab2cafa88f2a259ac7a6512","messageTitle":"Fix Checkstyle","messageBody":"","fileTypesAndContributionMap":{"functional-code":{"insertions":0,"deletions":2}}}]},{"date":"2021-03-30","commitResults":[{"hash":"8fc65222f6481b19c6a03b04e7929f9e72ad775a","messageTitle":"Change documentation for Storage folder","messageBody":"","fileTypesAndContributionMap":{"functional-code":{"insertions":61,"deletions":60},"test-code":{"insertions":0,"deletions":133}}}]},{"date":"2021-03-31","commitResults":[{"hash":"4f778e0dc0b5122f67c665d84693ae4539cd95e3","messageTitle":"Update User Guide to include EditBookingCommand","messageBody":"","fileTypesAndContributionMap":{"docs":{"insertions":23,"deletions":4}}},{"hash":"b092f5b913c6f8795b59f29e50b375960dc70a50","messageTitle":"Update User Guide","messageBody":"","fileTypesAndContributionMap":{"docs":{"insertions":1,"deletions":0}}}]}],"jaredtengsw":[{"date":"2021-02-21","commitResults":[{"hash":"182b014408006e9b2189f20fd151f3ba6c917676","messageTitle":"Update AboutUs.md","messageBody":"","fileTypesAndContributionMap":{"docs":{"insertions":4,"deletions":4}}}]},{"date":"2021-02-23","commitResults":[{"hash":"161dc7a7329edcad38d00a966877b94e028d5899","messageTitle":"Update README.md","messageBody":"","fileTypesAndContributionMap":{"docs":{"insertions":9,"deletions":10}}}]},{"date":"2021-02-24","commitResults":[{"hash":"82331e514d3bf53804e2906604f248ad4143b993","messageTitle":"Update UG: Help, HelpWindow.java","messageBody":"","fileTypesAndContributionMap":{"functional-code":{"insertions":1,"deletions":1},"docs":{"insertions":12,"deletions":10}}},{"hash":"fc29a98a4dfdcf39a9fb0167d25cffef80e2feba","messageTitle":"Update UG: Help, HelpWindow.java \u0026 README.md","messageBody":"","fileTypesAndContributionMap":{"docs":{"insertions":8,"deletions":6}}},{"hash":"56992ab9a4b890c931f0ef1c4798e77ba3219816","messageTitle":"Update HelpWindow.java to comply with checkStyle","messageBody":"","fileTypesAndContributionMap":{"functional-code":{"insertions":2,"deletions":1}}}]},{"date":"2021-02-28","commitResults":[{"hash":"88b56d290b139901dfc3af5547be10a53f5c16f4","messageTitle":"Update DeveloperGuide.md: Use Cases","messageBody":"","fileTypesAndContributionMap":{"docs":{"insertions":42,"deletions":57}}}]},{"date":"2021-03-04","commitResults":[{"hash":"6dac6f9d99fb5105ad5fddc70c592322c56683e9","messageTitle":"Update DeveloperGuide.md: Use Cases","messageBody":"","fileTypesAndContributionMap":{"docs":{"insertions":4,"deletions":3}}}]},{"date":"2021-03-14","commitResults":[{"hash":"700e7937a4e8b9890ea3009e7b7df3afca78c76e","messageTitle":"Morph Name attribute; Rename classes in residence package.","messageBody":"","fileTypesAndContributionMap":{"functional-code":{"insertions":15,"deletions":15},"other":{"insertions":14,"deletions":14}}},{"hash":"8efedbb9e645979e442f6026b80f09e3aa7a013e","messageTitle":"Morph Name attribute; Rename classes in residence package.","messageBody":"","fileTypesAndContributionMap":{"functional-code":{"insertions":16,"deletions":16}}}]},{"date":"2021-03-15","commitResults":[{"hash":"c760c19502b4b04a2e79f044de08b15b32829234","messageTitle":"Update help, list and find commands","messageBody":"","fileTypesAndContributionMap":{"functional-code":{"insertions":94,"deletions":55},"other":{"insertions":4,"deletions":4},"test-code":{"insertions":11,"deletions":11}}},{"hash":"7a94c2daee255f091113b12b1132e03d0bd23007","messageTitle":"Update help, list and find commands","messageBody":"","fileTypesAndContributionMap":{"functional-code":{"insertions":5,"deletions":5},"other":{"insertions":4,"deletions":4},"test-code":{"insertions":9,"deletions":9}}}]},{"date":"2021-03-16","commitResults":[{"hash":"ba014b92ce7e3a05785f1e88412c6012456fa62b","messageTitle":"Update EditResidenceDescriptorBuilder.java","messageBody":"Add newline at EOF","fileTypesAndContributionMap":{"test-code":{"insertions":1,"deletions":1}}},{"hash":"36f7fed7598970b3a5cd90be619e01eda7bfebe1","messageTitle":"Update testcases","messageBody":"","fileTypesAndContributionMap":{"test-code":{"insertions":226,"deletions":204}}},{"hash":"0b48e5d5ac04d98e3713aa7362b940ee6431ef4b","messageTitle":"Update test cases","messageBody":"","fileTypesAndContributionMap":{"test-code":{"insertions":188,"deletions":189}}},{"hash":"9a05c4e4b1ede2456f9786b7dccdd31461dfda54","messageTitle":"Update test cases, test utils and test json files","messageBody":"","fileTypesAndContributionMap":{"other":{"insertions":2,"deletions":2},"test-code":{"insertions":5,"deletions":5}}}]},{"date":"2021-03-18","commitResults":[{"hash":"407aa47855ed21f16f2f3a188954181a9cc7d898","messageTitle":"Update EditCommand.java to handle duplicate residences","messageBody":"","fileTypesAndContributionMap":{"functional-code":{"insertions":4,"deletions":0},"test-code":{"insertions":3,"deletions":2}}}]},{"date":"2021-03-21","commitResults":[{"hash":"89ddaa5247198cddc35a29a69ea83abd610f7927","messageTitle":"Fixed EditCommandTest equals() test","messageBody":"","fileTypesAndContributionMap":{"functional-code":{"insertions":4,"deletions":4}}}]},{"date":"2021-03-24","commitResults":[{"hash":"5f678bf1ec2ce067a04e59c91f46b8a1cec7b594","messageTitle":"Update label in ResidenceCard.java","messageBody":"","fileTypesAndContributionMap":{"functional-code":{"insertions":2,"deletions":2}}}]},{"date":"2021-03-27","commitResults":[{"hash":"f089e79a52eb4bea01119184c05e4f5f4c77d25d","messageTitle":"Fixed some errors and modified some formatting","messageBody":"","fileTypesAndContributionMap":{"functional-code":{"insertions":12,"deletions":11}}},{"hash":"b5750f71cdd8fc14b5f07cab55547a6d0f251b55","messageTitle":"Fixed some errors and modified some formatting","messageBody":"","fileTypesAndContributionMap":{"functional-code":{"insertions":2,"deletions":3}}},{"hash":"d741004ee1841917f499b5aa2d3b70ca6463542d","messageTitle":"Updating Ui files to show list of bookings under each residence","messageBody":"","fileTypesAndContributionMap":{"functional-code":{"insertions":128,"deletions":16}}},{"hash":"34d6286146de1965c333757b966ad7afb0d4954b","messageTitle":"Updating Ui files to show list of bookings under each residence","messageBody":"","fileTypesAndContributionMap":{"functional-code":{"insertions":109,"deletions":134}}},{"hash":"a8478a67a2d3b514f55e4c4cca2bcec54f233cd3","messageTitle":"Fixed checkstyle for SampleDataUtil.java","messageBody":"","fileTypesAndContributionMap":{"functional-code":{"insertions":16,"deletions":16}}}]},{"date":"2021-03-28","commitResults":[{"hash":"3cb4779e1f4583368b5b9c87dad5478d960b3fdb","messageTitle":"Modified Ui\u0027s bookinglist showcase from FlowPane to ScrollPane","messageBody":"","fileTypesAndContributionMap":{"functional-code":{"insertions":37,"deletions":21}}},{"hash":"beef8237cb5f0863e912036c31b33c3b86e7045e","messageTitle":"Updated Ui to allow bookinglist to stretch with MainWindow","messageBody":"","fileTypesAndContributionMap":{"functional-code":{"insertions":22,"deletions":14}}}]},{"date":"2021-03-29","commitResults":[{"hash":"90da15688fe527aab2b573351df1ebf8918b0d56","messageTitle":"Improved HelpWindow; Reflects changes to commands automatically","messageBody":"","fileTypesAndContributionMap":{"functional-code":{"insertions":185,"deletions":42},"test-code":{"insertions":0,"deletions":3}}}]},{"date":"2021-03-31","commitResults":[{"hash":"cc8dd3ef665f6242e07bca3a33bb7c18ec533eaf","messageTitle":"Improved HelpWindow; Reflects changes to commands automatically","messageBody":"","fileTypesAndContributionMap":{"functional-code":{"insertions":34,"deletions":67}}},{"hash":"15e0a6c538c0b67d446b81018fee0e83967ae440","messageTitle":"Fixed bug where long booking spills out of pink text highlight","messageBody":"","fileTypesAndContributionMap":{"functional-code":{"insertions":14,"deletions":25}}},{"hash":"0629baa06fcdd10c3f40a779e8f4d08b989d3a52","messageTitle":"Updated Ui: 3 colors for upcoming, occurring \u0026 expired bookings.","messageBody":"","fileTypesAndContributionMap":{"functional-code":{"insertions":33,"deletions":6}}}]},{"date":"2021-04-01","commitResults":[{"hash":"470fdca7ff316e411bc64a9b1646bdbfffa2dc1d","messageTitle":"Fixed bug due to functionality of FlowPane","messageBody":"","fileTypesAndContributionMap":{"functional-code":{"insertions":7,"deletions":2}}}]}],"wangtao0717":[{"date":"2021-02-21","commitResults":[{"hash":"597f1a1e7e726481bf2bc8acc6993e4b65b9786d","messageTitle":"update AboutUs--wangtao","messageBody":"","fileTypesAndContributionMap":{"docs":{"insertions":5,"deletions":5}}},{"hash":"ca8431994f39a32eca163053a71743f2ee30af97","messageTitle":"Update UG -Add Command","messageBody":"","fileTypesAndContributionMap":{"docs":{"insertions":5,"deletions":9}}}]},{"date":"2021-02-24","commitResults":[{"hash":"96573c931007d7eb18b383c06f3e9911ad49d3df","messageTitle":"Update UserGuide.md","messageBody":"","fileTypesAndContributionMap":{"docs":{"insertions":1,"deletions":1}}},{"hash":"cbf72430c0bed48383013228b4f91474e5589ea7","messageTitle":"Update AboutUs.md","messageBody":"","fileTypesAndContributionMap":{"docs":{"insertions":1,"deletions":1}}},{"hash":"e37e297f41c2b54e1800bf02a8cfa68429f2b843","messageTitle":"Rename wangtao.md to wangtao0717.md","messageBody":"","fileTypesAndContributionMap":{"docs":{"insertions":1,"deletions":0}}},{"hash":"33ae49e67ec805e504704fdd3e3de6f0385752cb","messageTitle":"Delete wangtao0717.md","messageBody":"","fileTypesAndContributionMap":{"docs":{"insertions":0,"deletions":1}}},{"hash":"bfcf42fc4f468779769e71fc2fff072f9b068dc7","messageTitle":"Update README.md","messageBody":"","fileTypesAndContributionMap":{"docs":{"insertions":9,"deletions":9}}}]},{"date":"2021-02-26","commitResults":[{"hash":"f5854e28260cc02d365a017e91cf7ef2d464356e","messageTitle":"Add photo and md file","messageBody":"","fileTypesAndContributionMap":{"docs":{"insertions":47,"deletions":0}}},{"hash":"e4b65bb6825eca7152e8c262b1483a6104f0b895","messageTitle":"update use case in developer guide","messageBody":"","fileTypesAndContributionMap":{"docs":{"insertions":94,"deletions":10}}}]},{"date":"2021-03-06","commitResults":[{"hash":"8af7426a05bb386a1405f214dac41835c501b03c","messageTitle":"morph clean status tag, add a new class CleanStatusTag","messageBody":"","fileTypesAndContributionMap":{"functional-code":{"insertions":291,"deletions":32},"test-code":{"insertions":22,"deletions":9}}},{"hash":"e030c75c81e1b4a6d3475441740428ee5a510e26","messageTitle":"improve for checkstyle","messageBody":"","fileTypesAndContributionMap":{"functional-code":{"insertions":30,"deletions":24}}},{"hash":"1a83cdffe9cdf7b9eb0205601db60cd10ea9342c","messageTitle":"improve for checkstyle","messageBody":"","fileTypesAndContributionMap":{"functional-code":{"insertions":42,"deletions":25}}},{"hash":"9ef9161f7cdbf0147b8bb6da2affa028c3d947b7","messageTitle":"solve small problem","messageBody":"","fileTypesAndContributionMap":{"functional-code":{"insertions":1,"deletions":1}}},{"hash":"4463fda30ab2e532942a2fe012e4ccd992eb59ef","messageTitle":"improve for checkstyle","messageBody":"","fileTypesAndContributionMap":{"functional-code":{"insertions":10,"deletions":8}}},{"hash":"232c425c2cfe7dd626d88c737cef8163b4ea831a","messageTitle":"improve","messageBody":"","fileTypesAndContributionMap":{"functional-code":{"insertions":4,"deletions":3}}},{"hash":"84c81d2bf79c0f7c89c450e78cb7eafebfdc3482","messageTitle":"improve","messageBody":"","fileTypesAndContributionMap":{"test-code":{"insertions":15,"deletions":2}}},{"hash":"164ab2390bb7b82fd262199514341f2d15ff8acb","messageTitle":"improve","messageBody":"","fileTypesAndContributionMap":{"test-code":{"insertions":20,"deletions":10}}}]},{"date":"2021-03-12","commitResults":[{"hash":"fa313d4b2047cedb116a76b8578cfd2a02b40064","messageTitle":"Update Logic.java","messageBody":"","fileTypesAndContributionMap":{"functional-code":{"insertions":1,"deletions":1}}},{"hash":"88a5b22304b44af030288bac9fbedadc5f993c21","messageTitle":"Update EditCommand.java","messageBody":"","fileTypesAndContributionMap":{"functional-code":{"insertions":1,"deletions":1}}},{"hash":"646c11ee569257ad2f073dc3d0c7dd024a08d0d3","messageTitle":"Update Logic.java","messageBody":"","fileTypesAndContributionMap":{"functional-code":{"insertions":1,"deletions":1}}}]},{"date":"2021-03-15","commitResults":[{"hash":"b663c21404147842eacaf0420d79bcdcab789f2c","messageTitle":"Update Ui","messageBody":"","fileTypesAndContributionMap":{"functional-code":{"insertions":52,"deletions":26}}},{"hash":"ce339f3fc6f4100c6a28fb4e589f768ba3c1bc52","messageTitle":"update background color","messageBody":"","fileTypesAndContributionMap":{"functional-code":{"insertions":2,"deletions":2}}}]},{"date":"2021-03-16","commitResults":[{"hash":"3bd38e1d0d0ec0f589714d2e8bd8c68a187708d6","messageTitle":"add a CleanStatusTagTest","messageBody":"","fileTypesAndContributionMap":{"test-code":{"insertions":41,"deletions":0}}},{"hash":"6bf214ebd6a8e8e7c32563c463b16527cbe58a45","messageTitle":"Update CleanStatusTagTest.java","messageBody":"","fileTypesAndContributionMap":{"test-code":{"insertions":1,"deletions":1}}},{"hash":"17bd91f218f4077a6d8ced5b9eda79b5c73992c1","messageTitle":"update test and edit command","messageBody":"","fileTypesAndContributionMap":{"functional-code":{"insertions":10,"deletions":0},"test-code":{"insertions":227,"deletions":226}}}]},{"date":"2021-03-19","commitResults":[{"hash":"be5fc0080c80a2a25d70a07b7e987416a69d70b2","messageTitle":"fix data path problem","messageBody":"","fileTypesAndContributionMap":{"test-code":{"insertions":2,"deletions":2}}}]},{"date":"2021-03-23","commitResults":[{"hash":"e75c0c4c229d09977baac11c0cfd301faa9669a9","messageTitle":"add new command status and some test of it","messageBody":"","fileTypesAndContributionMap":{"functional-code":{"insertions":164,"deletions":0},"test-code":{"insertions":145,"deletions":0}}},{"hash":"7b481e2ad792852dbda9d64874f2af4cfa8484be","messageTitle":"Comment out some tests to pass CI","messageBody":"","fileTypesAndContributionMap":{"test-code":{"insertions":99,"deletions":99}}}]},{"date":"2021-03-24","commitResults":[{"hash":"b8a2807519bbe07e64eb936adbe4d254c8edecd1","messageTitle":"Update StatusCommandTest.java","messageBody":"comment out a test","fileTypesAndContributionMap":{"test-code":{"insertions":15,"deletions":15}}},{"hash":"f131c89ebeab90427b234c1128a8fc7fde9cbad8","messageTitle":"change status file for refractoring from booking to bookinglist","messageBody":"","fileTypesAndContributionMap":{"functional-code":{"insertions":2,"deletions":2},"test-code":{"insertions":2,"deletions":2}}}]},{"date":"2021-03-28","commitResults":[{"hash":"bfff04269cb439e006cb9e4f95086f4b6a9c9025","messageTitle":"Update README.md","messageBody":"","fileTypesAndContributionMap":{"docs":{"insertions":1,"deletions":1}}},{"hash":"cb0a7da1d31dc7766d15ba948ba72f7e522ffe1e","messageTitle":"Update UserGuide.md","messageBody":"change the edit format","fileTypesAndContributionMap":{"docs":{"insertions":7,"deletions":5}}},{"hash":"bf25f2e647a1ff7b23bd0464edaa95f107cd7686","messageTitle":"change the background of Booklist and fix some size of demo window","messageBody":"","fileTypesAndContributionMap":{"functional-code":{"insertions":95,"deletions":89}}}]},{"date":"2021-03-29","commitResults":[{"hash":"4f0009f1dfefe0cc1c39c58358eb641370e12e24","messageTitle":"Update DarkTheme.css","messageBody":"","fileTypesAndContributionMap":{"functional-code":{"insertions":1,"deletions":1}}},{"hash":"d0d2371a2b7e473aa03fd73fc2e7ca75f47ebe3f","messageTitle":"abstract a CommonName from Name and ResidenceName","messageBody":"","fileTypesAndContributionMap":{"functional-code":{"insertions":2,"deletions":0}}},{"hash":"46a8a3fe38017ee0c8dff8254d859c5f09bf9027","messageTitle":"abstract a CommonName from Name and ResidenceName","messageBody":"","fileTypesAndContributionMap":{"functional-code":{"insertions":39,"deletions":31},"test-code":{"insertions":2,"deletions":2}}},{"hash":"88c2b9e9df2c53d51a3684372a45d3a6cb9ef9d5","messageTitle":"make ResidenceName class more restrictive, could contain\u0027@\u0027","messageBody":"","fileTypesAndContributionMap":{"functional-code":{"insertions":4,"deletions":6}}},{"hash":"f95659ff88131ed191975266d528b168e9acb550","messageTitle":"solve some relative test problem","messageBody":"","fileTypesAndContributionMap":{"functional-code":{"insertions":1,"deletions":1},"test-code":{"insertions":1,"deletions":1}}},{"hash":"82f7744bb364c2ee37f083b8fc975f97ee83d395","messageTitle":"new class BookingTime","messageBody":"","fileTypesAndContributionMap":{"functional-code":{"insertions":2,"deletions":0}}},{"hash":"cd42dd4acad49922bd4a04b1968fd119c1f253d5","messageTitle":"new class BookingTime","messageBody":"","fileTypesAndContributionMap":{"functional-code":{"insertions":94,"deletions":23}}},{"hash":"089b32323783ce0cd99be0562a70efc6a413d7bf","messageTitle":"check parser folder,  delete email parser and some test about it","messageBody":"","fileTypesAndContributionMap":{"functional-code":{"insertions":5,"deletions":28},"test-code":{"insertions":0,"deletions":27}}},{"hash":"ba9e58b1f8573c5bc95d595ed2256c70a658bc0a","messageTitle":"delete unuse files in ui folder","messageBody":"","fileTypesAndContributionMap":{"functional-code":{"insertions":0,"deletions":149}}}]},{"date":"2021-04-01","commitResults":[{"hash":"37e3e4501c32b60c8ed2ec2509e858b49770e582","messageTitle":"fix the bug that cant delete correct booking","messageBody":"","fileTypesAndContributionMap":{"functional-code":{"insertions":8,"deletions":0}}},{"hash":"fced0e281bdd2754a7c437297baa6ca217f8e94f","messageTitle":"add clean status to UG","messageBody":"","fileTypesAndContributionMap":{"docs":{"insertions":17,"deletions":1}}},{"hash":"20141b4603981068053924aa55e8c839352f12c6","messageTitle":"small change","messageBody":"","fileTypesAndContributionMap":{"docs":{"insertions":1,"deletions":1}}},{"hash":"2dc731fdfd73ef502bbd2067dad8630bba3483de","messageTitle":"small improve","messageBody":"","fileTypesAndContributionMap":{"docs":{"insertions":1,"deletions":0}}}]},{"date":"2021-04-04","commitResults":[{"hash":"2c248cac9043dae35e5c1ca60076f9d7ff79fef1","messageTitle":"fix status command bug by checking all index first","messageBody":"","fileTypesAndContributionMap":{"functional-code":{"insertions":4,"deletions":0}}},{"hash":"072ea1d7cdd1c9f83352c3ab80551e5f6623695f","messageTitle":"updeate UG for some issue","messageBody":"","fileTypesAndContributionMap":{"docs":{"insertions":23,"deletions":19}}},{"hash":"d1f5676761e1648ded12862beb36e4674831c41e","messageTitle":"fix edit command error\" Error message parameters does not match UG\"","messageBody":"","fileTypesAndContributionMap":{"functional-code":{"insertions":8,"deletions":2}}},{"hash":"d70e02af0decc07448bacd6aaba4c62f70cf7f2d","messageTitle":"update description of status","messageBody":"","fileTypesAndContributionMap":{"docs":{"insertions":1,"deletions":1}}},{"hash":"8f3e80c4a770f5cc960a20584bfd55caa013f8ae","messageTitle":"fix the bug when input 0 or negative number in RESIDENCE_INDEX or BOOKINGINDEX, demo can not show error message but \"Invalid command format message\"","messageBody":"","fileTypesAndContributionMap":{"functional-code":{"insertions":35,"deletions":25},"test-code":{"insertions":11,"deletions":10}}},{"hash":"2f24a094468b7798074b227f76068815cc7e8883","messageTitle":"improve","messageBody":"","fileTypesAndContributionMap":{"functional-code":{"insertions":1,"deletions":0}}},{"hash":"b61d33592a67fece6a492775b71c589ef9fb00d5","messageTitle":"update initial sample to make residece list sorted by clean status","messageBody":"","fileTypesAndContributionMap":{"functional-code":{"insertions":4,"deletions":3}}}]},{"date":"2021-04-05","commitResults":[{"hash":"d792f0754e410170a1bbcb3b845468d0e00503ea","messageTitle":"make most commented out test run correctly","messageBody":"","fileTypesAndContributionMap":{"functional-code":{"insertions":20,"deletions":4},"test-code":{"insertions":227,"deletions":238}}},{"hash":"bf835d39057606996d0330ad411190ea1f38dd20","messageTitle":"improve for checkstyle","messageBody":"","fileTypesAndContributionMap":{"functional-code":{"insertions":1,"deletions":1}}}]},{"date":"2021-04-08","commitResults":[{"hash":"268f11d5ce6f48229ddc6e800bfaca96306d0143","messageTitle":"update ppp and DG","messageBody":"","fileTypesAndContributionMap":{"docs":{"insertions":43,"deletions":24}}}]},{"date":"2021-04-10","commitResults":[{"hash":"6bd1b8e1dd7d401643f7b9e97769bde911d1d8e3","messageTitle":"Rename wangtao.md to wangtao0717.md","messageBody":"","fileTypesAndContributionMap":{"docs":{"insertions":0,"deletions":0}}}]}],"VRSoorya":[{"date":"2021-02-19","commitResults":[{"hash":"3b2e09aa574cbfbb5f404b4522fb5967ea834471","messageTitle":"Update index.md","messageBody":"Fix CI failure since the badge was pointing to upstream seedu AB3 repo","fileTypesAndContributionMap":{"docs":{"insertions":1,"deletions":1}}}]},{"date":"2021-02-23","commitResults":[{"hash":"f074623b5e2de3a23e4986a39f2a7ee018044252","messageTitle":"Update AboutUs - Soorya","messageBody":"","fileTypesAndContributionMap":{"docs":{"insertions":52,"deletions":5}}}]},{"date":"2021-02-24","commitResults":[{"hash":"fc34547b13dd27b76ad87fded37aa19504b8bbf8","messageTitle":"Update UG for find command","messageBody":"","fileTypesAndContributionMap":{"docs":{"insertions":8,"deletions":9}}},{"hash":"e72478f96fc055bedfa0ef921b6ddbfca63746cf","messageTitle":"Edit title of find command in UG","messageBody":"","fileTypesAndContributionMap":{"docs":{"insertions":1,"deletions":1}}},{"hash":"abe514790c63cc20750fabb9d272d821bcf1d52a","messageTitle":"Edit name of image file","messageBody":"","fileTypesAndContributionMap":{"docs":{"insertions":2,"deletions":2}}},{"hash":"651f752d6a0f6bf40e91ac4bcada18e1c28824fe","messageTitle":"Update AboutUs.md","messageBody":"","fileTypesAndContributionMap":{"docs":{"insertions":1,"deletions":1}}}]},{"date":"2021-02-28","commitResults":[{"hash":"5706e984d3f259b429fa3c36ab20d4e8a476a61b","messageTitle":"Update DG user stories","messageBody":"","fileTypesAndContributionMap":{"docs":{"insertions":9,"deletions":8}}},{"hash":"1fc49c27909453854d7e642b92c9ab17bb679343","messageTitle":"Add benefit for add residence user story","messageBody":"","fileTypesAndContributionMap":{"docs":{"insertions":2,"deletions":2}}}]},{"date":"2021-03-02","commitResults":[{"hash":"0fefadb282f47c167b91e52bea2dd56fa3ea1a41","messageTitle":"Update Residence.java","messageBody":"","fileTypesAndContributionMap":{"functional-code":{"insertions":4,"deletions":4}}},{"hash":"43bc07b8db98f40fb0482aef457f89b3b57df3a5","messageTitle":"Update UniqueResidenceList.java","messageBody":"","fileTypesAndContributionMap":{"functional-code":{"insertions":1,"deletions":1}}}]},{"date":"2021-03-07","commitResults":[{"hash":"f1a14eeb0a14ee295a7bed1ca196a8d6b70403a4","messageTitle":"Edit comments for address","messageBody":"","fileTypesAndContributionMap":{"functional-code":{"insertions":4,"deletions":2}}}]},{"date":"2021-03-15","commitResults":[{"hash":"e6a016848b3ccf7611a767f0c93b943c93ddcb4d","messageTitle":"WIP: correct test cases for residence","messageBody":"","fileTypesAndContributionMap":{"functional-code":{"insertions":57,"deletions":36},"test-code":{"insertions":811,"deletions":83}}},{"hash":"e76591024183ba782a46722732011d454e2a5eb8","messageTitle":"Edit to change cleanStatusTag to binary","messageBody":"","fileTypesAndContributionMap":{"functional-code":{"insertions":28,"deletions":40},"test-code":{"insertions":15,"deletions":12}}}]},{"date":"2021-03-16","commitResults":[{"hash":"50667b6d65870894e26a9eafef60de50209cb0e6","messageTitle":"Fix changes to clean status tag","messageBody":"","fileTypesAndContributionMap":{"functional-code":{"insertions":9,"deletions":28}}},{"hash":"b1d2132a638c4e5a79c5c703188a1b245740a849","messageTitle":"Fix UI after change in clean status","messageBody":"","fileTypesAndContributionMap":{"functional-code":{"insertions":7,"deletions":8}}},{"hash":"f6a1ed2af93326327f19bc9edab706eb9a495b81","messageTitle":"Refactor and edit Add command","messageBody":"","fileTypesAndContributionMap":{"functional-code":{"insertions":170,"deletions":103},"test-code":{"insertions":327,"deletions":342}}},{"hash":"0310208882d8a6ed17e91b9c65b9fe2aa28cc595","messageTitle":"Fix most breaking tests except the Parser classes","messageBody":"","fileTypesAndContributionMap":{"functional-code":{"insertions":59,"deletions":60},"other":{"insertions":7,"deletions":7},"test-code":{"insertions":365,"deletions":394}}}]},{"date":"2021-03-18","commitResults":[{"hash":"71744f569602601273f45e064a9ad104c35bf3da","messageTitle":"Fix some breaking tests","messageBody":"","fileTypesAndContributionMap":{"functional-code":{"insertions":33,"deletions":40},"other":{"insertions":0,"deletions":0},"test-code":{"insertions":97,"deletions":93}}}]},{"date":"2021-03-26","commitResults":[{"hash":"d8ee5ae89c2dd20f27ef7e5ed0641c047311be79","messageTitle":"Fix bug that changes clean status when typing edit INDEX","messageBody":"","fileTypesAndContributionMap":{"functional-code":{"insertions":24,"deletions":37},"test-code":{"insertions":1,"deletions":1}}},{"hash":"05a2b693b9aa79821b76cff7fc50693cc4af2e17","messageTitle":"Edit minor details","messageBody":"","fileTypesAndContributionMap":{"functional-code":{"insertions":3,"deletions":4}}},{"hash":"e82963966f981ffe8115302bfc1cb218a7032323","messageTitle":"Add BookingList","messageBody":"","fileTypesAndContributionMap":{"functional-code":{"insertions":179,"deletions":46},"test-code":{"insertions":27,"deletions":24}}},{"hash":"7bd985e17671bce21c617c775b10e2fabed27f3a","messageTitle":"Fix test","messageBody":"","fileTypesAndContributionMap":{"test-code":{"insertions":1,"deletions":1}}},{"hash":"d53e1eb86008dc0e53cebf63ac53535a5564a41c","messageTitle":"Add AddBookingCommand","messageBody":"","fileTypesAndContributionMap":{"functional-code":{"insertions":113,"deletions":25},"test-code":{"insertions":78,"deletions":75}}},{"hash":"bed1e38d52293b89358b6f3eca58f0bde74d31c1","messageTitle":"Add AddBookingCommandParse","messageBody":"","fileTypesAndContributionMap":{"functional-code":{"insertions":104,"deletions":23},"test-code":{"insertions":3,"deletions":3}}},{"hash":"2663ab367c924ef5016bbba8eef17b397d6e0dc6","messageTitle":"Print toString for sorted BookingList","messageBody":"","fileTypesAndContributionMap":{"functional-code":{"insertions":24,"deletions":6}}}]},{"date":"2021-03-27","commitResults":[{"hash":"1552146f30ecfe8d0428b3392303f9afeb0fa97a","messageTitle":"Fix bugs","messageBody":"","fileTypesAndContributionMap":{"functional-code":{"insertions":33,"deletions":26},"test-code":{"insertions":126,"deletions":41}}},{"hash":"44f22a89b318ab8d1fff69d1b0a884a9ffad3f38","messageTitle":"Fix more merge conflicts","messageBody":"","fileTypesAndContributionMap":{"functional-code":{"insertions":5,"deletions":7},"test-code":{"insertions":2,"deletions":76}}},{"hash":"1a08375f75370f7424cf3c8584c612b270a8eb3e","messageTitle":"Fix CommandException handling","messageBody":"","fileTypesAndContributionMap":{"functional-code":{"insertions":18,"deletions":3}}},{"hash":"fdf8420078990262c57fc91dd76720c0289fa3b2","messageTitle":"Comment out booking.UniqueBookingList","messageBody":"","fileTypesAndContributionMap":{"functional-code":{"insertions":136,"deletions":136}}},{"hash":"2c803489acea1059b5bd6a1e04adfbcf6e4ee11f","messageTitle":"Fix checkstyle","messageBody":"","fileTypesAndContributionMap":{"functional-code":{"insertions":2,"deletions":5}}},{"hash":"ca674ad415d108fec24ffa3e60d43d98fe8f2f8a","messageTitle":"Fix breaking tests","messageBody":"","fileTypesAndContributionMap":{"functional-code":{"insertions":1,"deletions":0},"test-code":{"insertions":107,"deletions":54}}},{"hash":"3ebabad3d5da418b90ccbfbb2261737a28d10faf","messageTitle":"Fix checkstyle","messageBody":"","fileTypesAndContributionMap":{"test-code":{"insertions":2,"deletions":2}}},{"hash":"2d60ac6227bc2bf0e11c7992e9404caec51ad0a8","messageTitle":"Fix checkstyle","messageBody":"","fileTypesAndContributionMap":{"test-code":{"insertions":1,"deletions":1}}},{"hash":"597641e07eb9752aae0619d9ec43f06e79d5c90d","messageTitle":"Remove print statements","messageBody":"","fileTypesAndContributionMap":{"functional-code":{"insertions":0,"deletions":1}}}]},{"date":"2021-03-31","commitResults":[{"hash":"bd3869403afe40207efb65f093ef549ce542c457","messageTitle":"Fix status command bug and some tests","messageBody":"","fileTypesAndContributionMap":{"functional-code":{"insertions":90,"deletions":378},"other":{"insertions":4,"deletions":1},"test-code":{"insertions":42,"deletions":417}}},{"hash":"8897875722f4c53045c56bfe46dfb5f8b6d6cc43","messageTitle":"Edit javadoc for model files","messageBody":"","fileTypesAndContributionMap":{"functional-code":{"insertions":66,"deletions":145},"other":{"insertions":16,"deletions":21},"docs":{"insertions":9,"deletions":9},"test-code":{"insertions":78,"deletions":78}}},{"hash":"0e7731eb732dec53006a149c88da01e1bfc9f0cf","messageTitle":"Fix checkstyle","messageBody":"","fileTypesAndContributionMap":{"functional-code":{"insertions":6,"deletions":5},"test-code":{"insertions":5,"deletions":3}}},{"hash":"d2be4f29e070d8274607941d3d8df96876b12f62","messageTitle":"Fix merge conflict","messageBody":"","fileTypesAndContributionMap":{"other":{"insertions":1,"deletions":1},"docs":{"insertions":4,"deletions":13}}},{"hash":"4c6978de728b07b36ac11d57cd403550396111d7","messageTitle":"Fix checkstyle","messageBody":"","fileTypesAndContributionMap":{"docs":{"insertions":5,"deletions":5}}}]},{"date":"2021-04-01","commitResults":[{"hash":"412066c473c3f7f8c20ead33cb889cdd0fd528b1","messageTitle":"Address PR comments","messageBody":"","fileTypesAndContributionMap":{"functional-code":{"insertions":3,"deletions":3},"docs":{"insertions":0,"deletions":747},"test-code":{"insertions":22,"deletions":102}}},{"hash":"d27c9fe8340791ef752a77daa1ed5a658511b3b6","messageTitle":"Fix error messages","messageBody":"","fileTypesAndContributionMap":{"functional-code":{"insertions":7,"deletions":6}}},{"hash":"11d097015cdba83541a4210b41ab1e8edb1d4358","messageTitle":"Fix test failures","messageBody":"","fileTypesAndContributionMap":{"test-code":{"insertions":2,"deletions":1}}},{"hash":"52e4d3ee6031bb052feeb8a7fa381adb21641d4c","messageTitle":"Add remind feature","messageBody":"","fileTypesAndContributionMap":{"functional-code":{"insertions":54,"deletions":2}}},{"hash":"bd10b2b32a2491577f835f658fe0902b6f8319c9","messageTitle":"Update user guide","messageBody":"","fileTypesAndContributionMap":{"docs":{"insertions":48,"deletions":26}}},{"hash":"ce47f0c5c434867f7bf0a0c8468b0971a9d2fd92","messageTitle":"Update UG","messageBody":"","fileTypesAndContributionMap":{"docs":{"insertions":5,"deletions":2}}},{"hash":"3a2d61add2293c38b0b52dd0cbd1719929f1b823","messageTitle":"Update UG","messageBody":"","fileTypesAndContributionMap":{"docs":{"insertions":4,"deletions":2}}},{"hash":"c2069268b7e57fc65bbbf9b2e611c1f1e8050b0a","messageTitle":"Update user guide","messageBody":"","fileTypesAndContributionMap":{"docs":{"insertions":10,"deletions":10}}},{"hash":"8849b44cb9b5775dcec0e1eeae29827d2c21f6c1","messageTitle":"Update user guide","messageBody":"","fileTypesAndContributionMap":{"docs":{"insertions":1,"deletions":1}}}]},{"date":"2021-04-02","commitResults":[{"hash":"52a690aa30e2721f2c885fd0e846b0457bca07a8","messageTitle":"Update DG","messageBody":"","fileTypesAndContributionMap":{"docs":{"insertions":22,"deletions":1}}}]},{"date":"2021-04-03","commitResults":[{"hash":"2a024654df72882bb055953e53746a44a3d7c58a","messageTitle":"Add logging and exception handling for parseDate","messageBody":"","fileTypesAndContributionMap":{"functional-code":{"insertions":32,"deletions":10}}}]}]},"authorFileTypeContributionMap":{"whatthelump":{"docs":44,"functional-code":506,"test-code":331,"other":4},"awzhenyi":{"docs":41,"functional-code":965,"test-code":160},"jaredtengsw":{"docs":54,"functional-code":380,"test-code":44},"wangtao0717":{"docs":140,"functional-code":459,"test-code":550},"VRSoorya":{"docs":137,"functional-code":602,"test-code":1254,"other":4}},"authorContributionVariance":{"whatthelump":31398.305,"awzhenyi":32075.941,"jaredtengsw":18339.797,"wangtao0717":22040.516,"VRSoorya":157953.97},"authorDisplayNameMap":{"whatthelump":"CS2103-T16-3 LIM ..GANG","awzhenyi":"CS2103-T16-3 AW Z..N YI","jaredtengsw":"CS2103-T16-3 TENG..ARED","wangtao0717":"CS2103-T16-3 WANG.. TAO","VRSoorya":"CS2103-T16-3 V R ..ORYA"}}
