{"authorDailyContributionsMap":{"kangtinglee":[],"Sharptail":[{"date":"2021-03-02","commitResults":[{"hash":"ac2d09aad6a3ef22ed019078383099c8560f710d","messageTitle":"Update README.md UI mockup and content","messageBody":"","fileTypesAndContributionMap":{"docs":{"insertions":8,"deletions":1}}},{"hash":"458fd9fcc3e9f42ff9d5bd385df23184d0e9d118","messageTitle":"Update index and AboutUs","messageBody":"","fileTypesAndContributionMap":{"docs":{"insertions":37,"deletions":36}}}]}],"guanyz":[{"date":"2021-03-02","commitResults":[{"hash":"d339b67ad16778e7d489b5c0045bc0c42d0b6c9b","messageTitle":"Update user stories for v1.1","messageBody":"","fileTypesAndContributionMap":{"docs":{"insertions":17,"deletions":10}}}]},{"date":"2021-03-04","commitResults":[{"hash":"89c1932809a5a8fd6c1b9ed2c67e6b1ddc2f3e4d","messageTitle":"Update NFRs, glossary","messageBody":"","fileTypesAndContributionMap":{"docs":{"insertions":7,"deletions":5}}}]}],"IanCKW":[{"date":"2021-03-02","commitResults":[{"hash":"3b6b98c2565653755cc073c0eec7ae064c0b23bb","messageTitle":"Update DeveloperGuide for v1.1","messageBody":"","fileTypesAndContributionMap":{"docs":{"insertions":273,"deletions":46}}},{"hash":"b012e9036f8d0cd6562643840e09e0a0332ae18d","messageTitle":"Update DeveloperGuide for v1.1","messageBody":"","fileTypesAndContributionMap":{"docs":{"insertions":27,"deletions":11}}}]}],"jamesleeht":[{"date":"2021-03-02","commitResults":[{"hash":"6bc8e7009988c5cd8ef33ca5b152891556f24e8a","messageTitle":"Update user guide","messageBody":"","fileTypesAndContributionMap":{"docs":{"insertions":123,"deletions":140}}}]},{"date":"2021-03-04","commitResults":[{"hash":"6a7ceac429c7249d6675ab8a30ec7bb69d9fa2f5","messageTitle":"Remove trace of AB3 from user guide","messageBody":"","fileTypesAndContributionMap":{"docs":{"insertions":1,"deletions":1}}}]}]},"authorFileTypeContributionMap":{"kangtinglee":{"docs":0,"functional-code":0,"test-code":0},"Sharptail":{"docs":45,"functional-code":0,"test-code":0},"guanyz":{"docs":22,"functional-code":0,"test-code":0},"IanCKW":{"docs":269,"functional-code":0,"test-code":0},"jamesleeht":{"docs":124,"functional-code":0,"test-code":0}},"authorContributionVariance":{"kangtinglee":0.0,"Sharptail":445.97964,"guanyz":54.596935,"IanCKW":8453.25,"jamesleeht":4582.6377},"authorDisplayNameMap":{"kangtinglee":"CS2103T-W15-3 LEE ..RCUS","Sharptail":"CS2103T-W15-3 KONG.. WEI","guanyz":"CS2103T-W15-3 GUAN..G ZE","IanCKW":"CS2103T-W15-3 IAN .. WAI","jamesleeht":"CS2103T-W15-3 LEE ..AMES"}}
